hello.py
eldarion-0.1.0.dist-info/METADATA
eldarion-0.1.0.dist-info/WHEEL
eldarion-0.1.0.dist-info/top_level.txt
eldarion-0.1.0.dist-info/RECORD
