Metadata-Version: 2.1
Name: eldarion
Version: 0.1.0
Summary: Add your description here
Requires-Python: >=3.10
Requires-Dist: ruff >=0.7.1
